odoo/addons/sale_blanket_order_date_confirmed/LICENSE
odoo/addons/sale_blanket_order_date_confirmed/README.rst
odoo/addons/sale_blanket_order_date_confirmed/__init__.py
odoo/addons/sale_blanket_order_date_confirmed/__manifest__.py
odoo/addons/sale_blanket_order_date_confirmed/images/screen.png
odoo/addons/sale_blanket_order_date_confirmed/models/__init__.py
odoo/addons/sale_blanket_order_date_confirmed/models/blanket_order.py
odoo/addons/sale_blanket_order_date_confirmed/static/description/icon.png
odoo/addons/sale_blanket_order_date_confirmed/static/description/index.html
odoo/addons/sale_blanket_order_date_confirmed/tests/TEST_INSTRUCTIONS.rst
odoo/addons/sale_blanket_order_date_confirmed/views/view_blanket_order_form.xml
odoo_addon_sale_blanket_order_date_confirmed-16.0.1.0.0.dist-info/METADATA
odoo_addon_sale_blanket_order_date_confirmed-16.0.1.0.0.dist-info/WHEEL
odoo_addon_sale_blanket_order_date_confirmed-16.0.1.0.0.dist-info/top_level.txt
odoo_addon_sale_blanket_order_date_confirmed-16.0.1.0.0.dist-info/RECORD
